foreverpy/__init__.py
foreverpy/hello.py
foreverpy-0.1.1.dist-info/METADATA
foreverpy-0.1.1.dist-info/WHEEL
foreverpy-0.1.1.dist-info/top_level.txt
foreverpy-0.1.1.dist-info/RECORD
