Metadata-Version: 2.2
Name: foreverpy
Version: 0.1.1
Summary: A simple greeting package
Author-email: Revati <kishorsinnur31@gmail.com>
License: MIT
Project-URL: Homepage, https://github.com/kishor-sinnur/forverpy
Keywords: greeting,python package
Requires-Python: >=3.11
